datastructure_collection/__init__.py
datastructure_collection/binarySearchTree.py
datastructure_collection/hashMap.py
datastructure_collection/linkedList.py
tests/__init__.py
tests/datastructure_example.py
tests/test_binary_search_tree.py
tests/test_hash_map.py
tests/test_linked_list.py
datastructure_collection_nyakaz73-0.0.1.dist-info/LICENSE
datastructure_collection_nyakaz73-0.0.1.dist-info/METADATA
datastructure_collection_nyakaz73-0.0.1.dist-info/WHEEL
datastructure_collection_nyakaz73-0.0.1.dist-info/top_level.txt
datastructure_collection_nyakaz73-0.0.1.dist-info/RECORD
